[
{"tag": "[其他]", "name": "回到三国的特种狙击手", "author": "东一方", "url": "http://www.cyuedu.com/list/15/15607.html"},
{"tag": "[都市]", "name": "女神老婆爱上我", "author": "刘家二少", "url": "http://www.cyuedu.com/list/30/30519.html"},
{"tag": "[武侠]", "name": "万古界圣", "author": "离殇断肠", "url": "http://www.cyuedu.com/list/103/103512.html"},
{"tag": "[其他]", "name": "绝品野医", "author": "悠然钟声", "url": "http://www.cyuedu.com/list/115/115112.html"},
{"tag": "[其他]", "name": "乡野透视高手", "author": "神话", "url": "http://www.cyuedu.com/list/115/115082.html"},
{"tag": "[历史]", "name": "天才纨绔", "author": "陌上猪猪", "url": "http://www.cyuedu.com/list/34/34168.html"},
{"tag": "[武侠]", "name": "史上最牛轮回", "author": "那一抹绯红", "url": "http://www.cyuedu.com/list/81/81852.html"},
{"tag": "[其他]", "name": "全球通缉心尖宠", "author": "洛心辰", "url": "http://www.cyuedu.com/list/121/121175.html"},
{"tag": "[其他]", "name": "特种医王", "author": "花园别墅888", "url": "http://www.cyuedu.com/list/121/121153.html"},
{"tag": "[玄幻]", "name": "武逆", "author": "只是小虾米", "url": "http://www.cyuedu.com/list/18/18262.html"},
{"tag": "[玄幻]", "name": "斗罗大陆4终极斗罗", "author": "唐家三少", "url": "http://www.cyuedu.com/list/117/117302.html"},
{"tag": "[其他]", "name": "逍遥小仙农", "author": "飞天小鲤鱼", "url": "http://www.cyuedu.com/list/121/121104.html"},
{"tag": "[玄幻]", "name": "终极斗罗", "author": "唐家三少", "url": "http://www.cyuedu.com/list/117/117227.html"},
{"tag": "[武侠]", "name": "史上最强炉鼎", "author": "青莲依无霜", "url": "http://www.cyuedu.com/list/88/88277.html"},
{"tag": "[女生]", "name": "重生之嫡女妖娆", "author": "帘霜", "url": "http://www.cyuedu.com/list/37/37656.html"},
{"tag": "[其他]", "name": "豪门囚情：凌少33次求婚", "author": "曲婉凌慕白", "url": "http://www.cyuedu.com/list/121/121058.html"},
{"tag": "[都市]", "name": "爱情蒙了眼", "author": "金子miss", "url": "http://www.cyuedu.com/list/121/121055.html"},
{"tag": "[都市]", "name": "萌宝来袭：爹地，这是我妈咪", "author": "麻辣千金", "url": "http://www.cyuedu.com/list/121/121053.html"},
{"tag": "[都市]", "name": "情非我愿(强宠)", "author": "湖坨坨", "url": "http://www.cyuedu.com/list/121/121051.html"},
{"tag": "[都市]", "name": "首长大人：诱宠萌妻", "author": "香雪宠儿", "url": "http://www.cyuedu.com/list/120/120980.html"},
{"tag": "[玄幻]", "name": "侠客行小说", "author": "金庸", "url": "http://www.cyuedu.com/list/120/120981.html"},
{"tag": "[都市]", "name": "合租医仙", "author": "白纸一箱", "url": "http://www.cyuedu.com/list/94/94216.html"},
{"tag": "[都市]", "name": "Boss太嚣张：老公，结婚吧", "author": "罗衣对雪", "url": "http://www.cyuedu.com/list/120/120967.html"},
{"tag": "[都市]", "name": "极品神医", "author": "贱走偏锋", "url": "http://www.cyuedu.com/list/86/86436.html"},
{"tag": "[都市]", "name": "匆匆那年", "author": "只爱金泰妍", "url": "http://www.cyuedu.com/list/64/64429.html"},
{"tag": "[其他]", "name": "修真归来", "author": "TV帝、", "url": "http://www.cyuedu.com/list/107/107308.html"},
{"tag": "[其他]", "name": "文娱不朽", "author": "潇潇清枫", "url": "http://www.cyuedu.com/list/119/119199.html"},
{"tag": "[其他]", "name": "错嫁替婚总裁", "author": "分花拂柳", "url": "http://www.cyuedu.com/list/115/115134.html"},
{"tag": "[其他]", "name": "娇妻在上：穆少，轻点疼", "author": "半夜扇风", "url": "http://www.cyuedu.com/list/115/115084.html"},
{"tag": "[其他]", "name": "我是美人鱼：老公，你别闹！", "author": "慢慢鱼", "url": "http://www.cyuedu.com/list/113/113054.html"},
{"tag": "[都市]", "name": "王牌近身保镖", "author": "臣虎", "url": "http://www.cyuedu.com/list/87/87722.html"},
{"tag": "[其他]", "name": "神级特工系统", "author": "青山桃谷", "url": "http://www.cyuedu.com/list/113/113231.html"},
{"tag": "[玄幻]", "name": "校园绝品狂徒", "author": "柳江南", "url": "http://www.cyuedu.com/list/15/15325.html"},
{"tag": "[其他]", "name": "强宠，小娇妻给我生个宝宝", "author": "乱舞", "url": "http://www.cyuedu.com/list/113/113959.html"},
{"tag": "[恐怖]", "name": "僵爱：僵尸王的新娘", "author": "欧阳莉", "url": "http://www.cyuedu.com/list/87/87721.html"},
{"tag": "[女生]", "name": "战神比肩：绝色战王", "author": "紫萧灵", "url": "http://www.cyuedu.com/list/87/87544.html"},
{"tag": "[玄幻]", "name": "斋公", "author": "世纪之燕", "url": "http://www.cyuedu.com/list/110/110390.html"},
{"tag": "[都市]", "name": "全能透视", "author": "寻北仪", "url": "http://www.cyuedu.com/list/86/86563.html"},
{"tag": "[其他]", "name": "庶女狂妃：神医炼丹师", "author": "杨家二小姐", "url": "http://www.cyuedu.com/list/117/117359.html"},
{"tag": "[历史]", "name": "夺鼎1617", "author": "猛将如云", "url": "http://www.cyuedu.com/list/30/30486.html"},
{"tag": "[女生]", "name": "神秘老公，晚上见！", "author": "碧玉萧", "url": "http://www.cyuedu.com/list/87/87742.html"},
{"tag": "[玄幻]", "name": "第一宠婚：军爷的头号新妻", "author": "雾初雪", "url": "http://www.cyuedu.com/list/120/120850.html"},
{"tag": "[都市]", "name": "延禧攻略小说", "author": "笑脸猫", "url": "http://www.cyuedu.com/list/120/120846.html"},
{"tag": "[其他]", "name": "除灵老师提不起劲", "author": "猫死由好奇心", "url": "http://www.cyuedu.com/list/118/118206.html"},
{"tag": "[其他]", "name": "极品透视神眼", "author": "寒江独钓", "url": "http://www.cyuedu.com/list/115/115089.html"},
{"tag": "[其他]", "name": "甜宠百分百：夺爱进行时", "author": "蒙七七", "url": "http://www.cyuedu.com/list/120/120797.html"},
{"tag": "[都市]", "name": "我的白蛇老公柳龙庭", "author": "白静", "url": "http://www.cyuedu.com/list/120/120793.html"},
{"tag": "[玄幻]", "name": "魔法傲世录", "author": "欧阳夏风", "url": "http://www.cyuedu.com/list/95/95522.html"},
{"tag": "[其他]", "name": "大王饶命", "author": "会说话的肘子", "url": "http://www.cyuedu.com/list/110/110559.html"},
{"tag": "[都市]", "name": "都市最强装逼系统", "author": "必火", "url": "http://www.cyuedu.com/list/97/97869.html"},
{"tag": "[历史]", "name": "市井贵女", "author": "双子座尧尧", "url": "http://www.cyuedu.com/list/35/35883.html"},
{"tag": "[都市]", "name": "嫡女至上：太子魔性宠", "author": "枯藤新枝", "url": "http://www.cyuedu.com/list/120/120779.html"},
{"tag": "[都市]", "name": "妈咪宝贝：总裁爹地超给力", "author": "林墨歌权简璃", "url": "http://www.cyuedu.com/list/120/120720.html"},
{"tag": "[其他]", "name": "你好秦医生", "author": "夜蔓", "url": "http://www.cyuedu.com/list/120/120617.html"},
{"tag": "[都市]", "name": "原来你还在这里", "author": "辛夷坞", "url": "http://www.cyuedu.com/list/120/120612.html"},
{"tag": "[都市]", "name": "唯愿君心似我心", "author": "甜小丫", "url": "http://www.cyuedu.com/list/120/120389.html"},
{"tag": "[都市]", "name": "来不及见你一面", "author": "落亦雪", "url": "http://www.cyuedu.com/list/120/120385.html"},
{"tag": "[其他]", "name": "绝望游戏", "author": "宁采臣", "url": "http://www.cyuedu.com/list/113/113775.html"},
{"tag": "[历史]", "name": "花与剑与法兰西", "author": "匂宮出夢", "url": "http://www.cyuedu.com/list/39/39149.html"},
{"tag": "[其他]", "name": "你是我幽冷的深渊", "author": "苦苦", "url": "http://www.cyuedu.com/list/120/120377.html"}
]